[
    {
        "id": "pizza-01",
        "name": "Pizza Margherita Supreme",
        "category": "Plats",
        "shortDesc": "La classique revisitée.",
        "fullDesc": "Tomates San Marzano, Mozzarella di Bufala, Basilic frais, Huile d'olive vierge. Une pâte fermentée 72h pour un croustillant incomparable.",
        "price": 14.50,
        "image2D": "https://placehold.co/600x400/png?text=Pizza+Margherita",
        "modelUrl": "/assets/models/pizza.glb",
        "dimensions": "Diamètre 30cm",
        "variants": [
            {
                "size": "M",
                "label": "M (30cm)",
                "priceModifier": 0,
                "scale": "1 1 1"
            },
            {
                "size": "L",
                "label": "L (40cm)",
                "priceModifier": 5.00,
                "scale": "1.33 1.33 1.33"
            }
        ],
        "hotspots": [
            {
                "slot": "cheese",
                "pos": "0.1m 0.05m 0.1m",
                "label": "Mozzarella AOP",
                "detail": "Mozzarella Di Bufala - Provenance : Italie, fraîchement importée."
            },
            {
                "slot": "basil",
                "pos": "-0.1m 0.05m 0.0m",
                "label": "Basilic Bio",
                "detail": "Basilic bio, cultivé dans notre jardin local."
            },
            {
                "slot": "tomato",
                "pos": "0m 0.02m 0m",
                "label": "Tomates San Marzano",
                "detail": "Tomates San Marzano DOP, récoltées à maturité en Campanie."
            }
        ],
        "nutrition": {
            "calories": 800,
            "allergenes": [
                "Gluten",
                "Lactose"
            ],
            "temps": "12 min"
        }
    },
    {
        "id": "burger-01",
        "name": "Burger Signature",
        "category": "Plats",
        "shortDesc": "Le burger définitif.",
        "fullDesc": "Steak haché Charolais, Cheddar affiné 12 mois, Sauce secrète, Oignons caramélisés.",
        "price": 16.00,
        "image2D": "https://placehold.co/600x400/png?text=Burger+Signature",
        "modelUrl": "/assets/models/burger.glb",
        "dimensions": "Hauteur 15cm",
        "variants": [
            {
                "size": "Simple",
                "label": "Simple",
                "priceModifier": 0,
                "scale": "1 1 1"
            },
            {
                "size": "Double",
                "label": "Double Steak",
                "priceModifier": 4.00,
                "scale": "1 1.2 1"
            }
        ],
        "hotspots": [
            {
                "slot": "cheddar",
                "pos": "0m 0.1m 0m",
                "label": "Cheddar Somerset",
                "detail": "Cheddar Somerset affiné 12 mois - Angleterre."
            },
            {
                "slot": "steak",
                "pos": "0m 0.05m 0m",
                "label": "Steak Charolais",
                "detail": "Steak haché Charolais, viande française de qualité supérieure."
            },
            {
                "slot": "onion",
                "pos": "0.05m 0.08m 0m",
                "label": "Oignons caramélisés",
                "detail": "Oignons caramélisés au beurre, mijotés 30 minutes."
            }
        ],
        "nutrition": {
            "calories": 950,
            "allergenes": [
                "Gluten",
                "Lactose",
                "Moutarde"
            ],
            "temps": "15 min"
        }
    },
    {
        "id": "dessert-01",
        "name": "Tiramisu della Nonna",
        "category": "Desserts",
        "shortDesc": "Recette traditionnelle.",
        "fullDesc": "Mascarpone onctueux, Savoiardi imbibés de café espresso, Cacao amer.",
        "price": 8.50,
        "image2D": "https://placehold.co/600x400/png?text=Tiramisu",
        "modelUrl": "/assets/models/dessert.glb",
        "dimensions": "Part généreuse",
        "variants": [
            {
                "size": "Classique",
                "label": "Part",
                "priceModifier": 0,
                "scale": "1 1 1"
            }
        ],
        "hotspots": [
            {
                "slot": "mascarpone",
                "pos": "0m 0.05m 0m",
                "label": "Mascarpone",
                "detail": "Mascarpone onctueux - Fromage frais italien de Lombardie."
            },
            {
                "slot": "coffee",
                "pos": "0m 0.08m 0m",
                "label": "Café espresso",
                "detail": "Savoiardi imbibés de café espresso italien, torréfaction moyenne."
            },
            {
                "slot": "cocoa",
                "pos": "0m 0.1m 0m",
                "label": "Cacao",
                "detail": "Cacao amer de qualité supérieure, saupoudré à la main."
            }
        ],
        "nutrition": {
            "calories": 450,
            "allergenes": [
                "Gluten",
                "Lactose",
                "Œuf"
            ],
            "temps": "Prêt"
        }
    },
    {
        "id": "chef-01",
        "name": "Plat du Chef",
        "category": "Plats",
        "shortDesc": "Création exclusive du chef.",
        "fullDesc": "Une création unique qui allie saveurs et présentation exceptionnelle.",
        "price": 22.00,
        "image2D": "https://placehold.co/600x400/png?text=Plat+du+Chef",
        "modelUrl": "/assets/models/menu-item.glb",
        "dimensions": "Portion généreuse",
        "variants": [
            {
                "size": "Standard",
                "label": "Standard",
                "priceModifier": 0,
                "scale": "1 1 1"
            }
        ],
        "hotspots": [],
        "nutrition": {
            "calories": 750,
            "allergenes": [],
            "temps": "20 min"
        }
    }
]
